infrared_tripleo_undercloud-3.0.0.dist-info/DESCRIPTION.rst
infrared_tripleo_undercloud-3.0.0.dist-info/METADATA
infrared_tripleo_undercloud-3.0.0.dist-info/RECORD
infrared_tripleo_undercloud-3.0.0.dist-info/WHEEL
infrared_tripleo_undercloud-3.0.0.dist-info/entry_points.txt
infrared_tripleo_undercloud-3.0.0.dist-info/metadata.json
infrared_tripleo_undercloud-3.0.0.dist-info/pbr.json
infrared_tripleo_undercloud-3.0.0.dist-info/top_level.txt
tripleo_undercloud/__init__.py
tripleo_undercloud/backup.yml
tripleo_undercloud/clouds.yml
tripleo_undercloud/configure.yml
tripleo_undercloud/create_user.yml
tripleo_undercloud/deploy.yml
tripleo_undercloud/hypervisor.yml
tripleo_undercloud/images.yml
tripleo_undercloud/init.yml
tripleo_undercloud/main.yml
tripleo_undercloud/plugin.spec
tripleo_undercloud/post.yml
tripleo_undercloud/restore.yml
tripleo_undercloud/setup_packages.yml
tripleo_undercloud/shade.yml
tripleo_undercloud/splitstack.yml
tripleo_undercloud/tls_everywhere.yml
tripleo_undercloud/undercloud.yml
tripleo_undercloud/upgrade.yml
tripleo_undercloud/validate.yml
tripleo_undercloud/version.yml
tripleo_undercloud/tasks/inject_undercloud_conf.yml
tripleo_undercloud/tasks/ssl.yml
tripleo_undercloud/tasks/images/build.yml
tripleo_undercloud/tasks/images/import.yml
tripleo_undercloud/tasks/images/repos.yml
tripleo_undercloud/tasks/images/rpm.yml
tripleo_undercloud/tasks/upgrade/upgrade.yml
tripleo_undercloud/tasks/upgrade/validation.yml
tripleo_undercloud/templates/undercloud.conf.j2
tripleo_undercloud/templates/undercloud_deploy.sh.j2
tripleo_undercloud/templates/undercloud_ospdui.conf
tripleo_undercloud/vars/cdn/cnd_creds.yml.sample
tripleo_undercloud/vars/ssl/defaults.yml
tripleo_undercloud/vars/topology/undercloud.yml
